sortpython/__init__.py
sortpython/algorithms/BubbleSort.py
sortpython/algorithms/CountingSort.py
sortpython/algorithms/InsertionSort.py
sortpython/algorithms/MergeSort.py
sortpython/algorithms/TimSort.py
sortpython/algorithms/__init__.py
sortpython/shared/Sort.py
sortpython/shared/__init__.py
sortpython/visualize/SortVisualizer.py
sortpython/visualize/__init__.py
sortpython-0.0.3.dist-info/METADATA
sortpython-0.0.3.dist-info/WHEEL
sortpython-0.0.3.dist-info/top_level.txt
sortpython-0.0.3.dist-info/RECORD
