Metadata-Version: 2.1
Name: sortpython
Version: 0.0.3
Summary: A Python package for various sorting algorithms
Home-page: https://github.com/rukmals/sortpy
Author: Rukmal Senavirathne
Classifier: Programming Language :: Python :: 3
Classifier: License :: OSI Approved :: MIT License
Classifier: Operating System :: OS Independent
Requires-Python: >=3.6
Requires-Dist: matplotlib
